LICENSE.txt
setup.cfg
setup.py
bigoyster/Bigoyster.py
bigoyster/__init__.py
bigoyster.egg-info/PKG-INFO
bigoyster.egg-info/SOURCES.txt
bigoyster.egg-info/dependency_links.txt
bigoyster.egg-info/top_level.txt